{
    "courses": [
        {
            "catalogTitle": "BMI 605",
            "section": "001",
            "courseTitle": "Intro to Telehealth"
        },
        {
            "catalogTitle": "BMI 6050",
            "section": "001",
            "courseTitle": "Intro to Telehealth"
        },
        {
            "catalogTitle": "BMI 6950",
            "section": "001",
            "courseTitle": "Special Topics"
        },
        {
            "catalogTitle": "BMI 6950",
            "section": "003",
            "courseTitle": "Special Topics"
        },
        {
            "catalogTitle": "BMI 6950",
            "section": "004",
            "courseTitle": "Global Health Practicum"
        },
        {
            "catalogTitle": "BMI 6950",
            "section": "005",
            "courseTitle": "Global Health Practicum"
        },
        {
            "catalogTitle": "BMI 6970",
            "section": "001",
            "courseTitle": "Thesis Research - M.S."
        },
        {
            "catalogTitle": "BMI 6975",
            "section": "001",
            "courseTitle": "Non-Thesis Caps Proj MS"
        },
        {
            "catalogTitle": "BMI 7902",
            "section": "001",
            "courseTitle": "BMI Practicum"
        },
        {
            "catalogTitle": "BMI 7970",
            "section": "001",
            "courseTitle": "Thesis Research - Ph.D."
        },
        {
            "catalogTitle": "BMI 7990",
            "section": "001",
            "courseTitle": "Cont Registration - PhD"
        }
    ]
}