{
    "courses": [
        {
            "catalogTitle": "LLHL 102",
            "section": "001",
            "courseTitle": "Yoga Experiential Retreat"
        },
        {
            "catalogTitle": "LLHL 108",
            "section": "001",
            "courseTitle": "Sugar & A Healthy Diet"
        },
        {
            "catalogTitle": "LLHL 129",
            "section": "001",
            "courseTitle": "Women's Strength Camp"
        },
        {
            "catalogTitle": "LLHL 131",
            "section": "001",
            "courseTitle": "Relationship Unities"
        },
        {
            "catalogTitle": "LLHL 138",
            "section": "001",
            "courseTitle": "Horses and Wellness"
        },
        {
            "catalogTitle": "LLHL 143",
            "section": "001",
            "courseTitle": "Tibetan Buddhist Meditation"
        },
        {
            "catalogTitle": "LLHL 181",
            "section": "001",
            "courseTitle": "The Meditation Experience"
        },
        {
            "catalogTitle": "LLHL 220",
            "section": "001",
            "courseTitle": "Being with Horses"
        },
        {
            "catalogTitle": "LLHL 223",
            "section": "001",
            "courseTitle": "Homemade Lotion"
        },
        {
            "catalogTitle": "LLHL 226",
            "section": "001",
            "courseTitle": "Intro to the Enneagram"
        },
        {
            "catalogTitle": "LLHL 228",
            "section": "001",
            "courseTitle": "How to Sleep When the World is"
        },
        {
            "catalogTitle": "LLHL 230",
            "section": "001",
            "courseTitle": "Individualize Your Yoga Practi"
        },
        {
            "catalogTitle": "LLHL 231",
            "section": "001",
            "courseTitle": "Imagining Life"
        },
        {
            "catalogTitle": "LLHL 232",
            "section": "002",
            "courseTitle": "The Four Noble Truths"
        }
    ]
}