{
    "courses": [
        {
            "catalogTitle": "MST 6011",
            "section": "001",
            "courseTitle": "Sustainable Business"
        },
        {
            "catalogTitle": "MST 6021",
            "section": "001",
            "courseTitle": "Strategy and Marketing"
        },
        {
            "catalogTitle": "MST 6022",
            "section": "001",
            "courseTitle": "Operations Management"
        },
        {
            "catalogTitle": "MST 6975",
            "section": "001",
            "courseTitle": "Internship"
        },
        {
            "catalogTitle": "MST 6980",
            "section": "001",
            "courseTitle": "Faculty Consultation"
        }
    ]
}