{
    "courses": [
        {
            "catalogTitle": "YECU 30",
            "section": "001",
            "courseTitle": "Leaders In Training (L.I.T.)"
        },
        {
            "catalogTitle": "YECU 601",
            "section": "001",
            "courseTitle": "The Summer Awakens (5-11)"
        },
        {
            "catalogTitle": "YECU 601",
            "section": "002",
            "courseTitle": "The Summer Awakens (5-11)"
        },
        {
            "catalogTitle": "YECU 601",
            "section": "003",
            "courseTitle": "The Summer Awakens (5-11)"
        },
        {
            "catalogTitle": "YECU 602",
            "section": "001",
            "courseTitle": "Worldly Wanderers (5-11)"
        },
        {
            "catalogTitle": "YECU 602",
            "section": "002",
            "courseTitle": "Worldly Wanderers (5-11)"
        },
        {
            "catalogTitle": "YECU 602",
            "section": "003",
            "courseTitle": "Worldly Wanderers (5-11)"
        },
        {
            "catalogTitle": "YECU 603",
            "section": "001",
            "courseTitle": "Cosmic Campers (5-11)"
        },
        {
            "catalogTitle": "YECU 603",
            "section": "002",
            "courseTitle": "Cosmic Campers (5-11)"
        },
        {
            "catalogTitle": "YECU 603",
            "section": "003",
            "courseTitle": "Cosmic Campers (5-11)"
        },
        {
            "catalogTitle": "YECU 604",
            "section": "001",
            "courseTitle": "SCIBOs Water World (5-11)"
        },
        {
            "catalogTitle": "YECU 604",
            "section": "002",
            "courseTitle": "SCIBOs Water World (5-11)"
        },
        {
            "catalogTitle": "YECU 604",
            "section": "003",
            "courseTitle": "SCIBOs Water World (5-11)"
        },
        {
            "catalogTitle": "YECU 605",
            "section": "001",
            "courseTitle": "Fantasy Factory (5-11)"
        },
        {
            "catalogTitle": "YECU 605",
            "section": "002",
            "courseTitle": "Fantasy Factory (5-11)"
        },
        {
            "catalogTitle": "YECU 605",
            "section": "003",
            "courseTitle": "Fantasy Factory (5-11)"
        },
        {
            "catalogTitle": "YECU 606",
            "section": "001",
            "courseTitle": "Excellent Adventure (5-11)"
        },
        {
            "catalogTitle": "YECU 606",
            "section": "002",
            "courseTitle": "Excellent Adventure (5-11)"
        },
        {
            "catalogTitle": "YECU 606",
            "section": "003",
            "courseTitle": "Excellent Adventure (5-11)"
        },
        {
            "catalogTitle": "YECU 607",
            "section": "001",
            "courseTitle": "The Secrets of STEM (5-11)"
        },
        {
            "catalogTitle": "YECU 607",
            "section": "002",
            "courseTitle": "The Secrets of STEM (5-11)"
        },
        {
            "catalogTitle": "YECU 607",
            "section": "003",
            "courseTitle": "The Secrets of STEM (5-11)"
        },
        {
            "catalogTitle": "YECU 608",
            "section": "001",
            "courseTitle": "Into the Blue w/ Club U (5-11)"
        },
        {
            "catalogTitle": "YECU 608",
            "section": "002",
            "courseTitle": "Into the Blue w/ Club U (5-11)"
        },
        {
            "catalogTitle": "YECU 608",
            "section": "003",
            "courseTitle": "Into the Blue w/ Club U (5-11)"
        },
        {
            "catalogTitle": "YECU 609",
            "section": "001",
            "courseTitle": "It's Show Time! (5-11)"
        },
        {
            "catalogTitle": "YECU 609",
            "section": "002",
            "courseTitle": "It's Show Time! (5-11)"
        },
        {
            "catalogTitle": "YECU 609",
            "section": "003",
            "courseTitle": "It's Show Time! (5-11)"
        },
        {
            "catalogTitle": "YECU 610",
            "section": "001",
            "courseTitle": "Go for the Gold (5-11)"
        },
        {
            "catalogTitle": "YECU 610",
            "section": "002",
            "courseTitle": "Go for the Gold (5-11)"
        },
        {
            "catalogTitle": "YECU 610",
            "section": "003",
            "courseTitle": "Go for the Gold (5-11)"
        },
        {
            "catalogTitle": "YECU 611",
            "section": "001",
            "courseTitle": "Splish-Splash Bash (5-11)"
        },
        {
            "catalogTitle": "YECU 611",
            "section": "002",
            "courseTitle": "Splish-Splash Bash (5-11)"
        },
        {
            "catalogTitle": "YECU 611",
            "section": "003",
            "courseTitle": "Splish-Splash Bash (5-11)"
        },
        {
            "catalogTitle": "YECU 621",
            "section": "001",
            "courseTitle": "Club U Varsity: Week 1 (12-14)"
        },
        {
            "catalogTitle": "YECU 622",
            "section": "001",
            "courseTitle": "Club U Varsity: Week 2 (12-14)"
        },
        {
            "catalogTitle": "YECU 623",
            "section": "001",
            "courseTitle": "Club U Varsity: Week 3 (12-14)"
        },
        {
            "catalogTitle": "YECU 624",
            "section": "001",
            "courseTitle": "Club U Varsity: Week 4 (12-14)"
        },
        {
            "catalogTitle": "YECU 625",
            "section": "001",
            "courseTitle": "Club U Varsity: Week 5 (12-14)"
        },
        {
            "catalogTitle": "YECU 626",
            "section": "001",
            "courseTitle": "Club U Varsity: Week 6 (12-14)"
        },
        {
            "catalogTitle": "YECU 627",
            "section": "001",
            "courseTitle": "Club U Varsity: Week 7 (12-14)"
        },
        {
            "catalogTitle": "YECU 628",
            "section": "001",
            "courseTitle": "Club U Varsity: Week 8 (12-14)"
        },
        {
            "catalogTitle": "YECU 629",
            "section": "001",
            "courseTitle": "Club U Varsity: Week 9 (12-14)"
        },
        {
            "catalogTitle": "YECU 630",
            "section": "001",
            "courseTitle": "Club U Varsity: Week10 (12-14)"
        },
        {
            "catalogTitle": "YECU 631",
            "section": "001",
            "courseTitle": "Club U Varsity: Week11 (12-14)"
        },
        {
            "catalogTitle": "YECU 900",
            "section": "001",
            "courseTitle": "Two Day Lounge (Age 5-14)"
        },
        {
            "catalogTitle": "YECU 900",
            "section": "002",
            "courseTitle": "Two Day Lounge (Age 5-14)"
        },
        {
            "catalogTitle": "YECU 900",
            "section": "003",
            "courseTitle": "Two Day Lounge (Age 5-14)"
        },
        {
            "catalogTitle": "YECU 900",
            "section": "004",
            "courseTitle": "Two Day Lounge (Age 5-14)"
        },
        {
            "catalogTitle": "YECU 900",
            "section": "005",
            "courseTitle": "Two Day Lounge (Age 5-14)"
        },
        {
            "catalogTitle": "YECU 900",
            "section": "006",
            "courseTitle": "Two Day Lounge (Age 5-14)"
        },
        {
            "catalogTitle": "YECU 900",
            "section": "007",
            "courseTitle": "Two Day Lounge (Age 5-14)"
        },
        {
            "catalogTitle": "YECU 900",
            "section": "008",
            "courseTitle": "Two Day Lounge (Age 5-14)"
        },
        {
            "catalogTitle": "YECU 900",
            "section": "009",
            "courseTitle": "Two Day Lounge (Age 5-14)"
        },
        {
            "catalogTitle": "YECU 900",
            "section": "010",
            "courseTitle": "Two Day Lounge (Age 5-14)"
        },
        {
            "catalogTitle": "YECU 900",
            "section": "011",
            "courseTitle": "Two Day Lounge (Age 5-14)"
        },
        {
            "catalogTitle": "YECU 901",
            "section": "001",
            "courseTitle": "Five Day Lounge (Age 5-14)"
        },
        {
            "catalogTitle": "YECU 901",
            "section": "002",
            "courseTitle": "Five Day Lounge (Age 5-14)"
        },
        {
            "catalogTitle": "YECU 901",
            "section": "003",
            "courseTitle": "Five Day Lounge (Age 5-14)"
        },
        {
            "catalogTitle": "YECU 901",
            "section": "004",
            "courseTitle": "Five Day Lounge (Age 5-14)"
        },
        {
            "catalogTitle": "YECU 901",
            "section": "005",
            "courseTitle": "Five Day Lounge (Age 5-14)"
        },
        {
            "catalogTitle": "YECU 901",
            "section": "006",
            "courseTitle": "Five Day Lounge (Age 5-14)"
        },
        {
            "catalogTitle": "YECU 901",
            "section": "007",
            "courseTitle": "Five Day Lounge (Age 5-14)"
        },
        {
            "catalogTitle": "YECU 901",
            "section": "008",
            "courseTitle": "Five Day Lounge (Age 5-14)"
        },
        {
            "catalogTitle": "YECU 901",
            "section": "009",
            "courseTitle": "Five Day Lounge (Age 5-14)"
        },
        {
            "catalogTitle": "YECU 901",
            "section": "010",
            "courseTitle": "Five Day Lounge (Age 5-14)"
        },
        {
            "catalogTitle": "YECU 901",
            "section": "011",
            "courseTitle": "Five Day Lounge (Age 5-14)"
        }
    ]
}