{
    "courses": [
        {
            "catalogTitle": "ELP 3410",
            "section": "001",
            "courseTitle": "Teachers and the Law"
        },
        {
            "catalogTitle": "ELP 6050",
            "section": "060",
            "courseTitle": "Program Planning & Eval"
        },
        {
            "catalogTitle": "ELP 6130",
            "section": "001",
            "courseTitle": "Collab Ed Decsn Mak"
        },
        {
            "catalogTitle": "ELP 6310",
            "section": "001",
            "courseTitle": "Instructional Ldship"
        },
        {
            "catalogTitle": "ELP 6330",
            "section": "001",
            "courseTitle": "Instructional Ldrship"
        },
        {
            "catalogTitle": "ELP 6330",
            "section": "070",
            "courseTitle": "Instructional Ldrship"
        },
        {
            "catalogTitle": "ELP 6410",
            "section": "001",
            "courseTitle": "Education Law"
        },
        {
            "catalogTitle": "ELP 6410",
            "section": "070",
            "courseTitle": "Education Law"
        },
        {
            "catalogTitle": "ELP 6500",
            "section": "001",
            "courseTitle": "Foundations of H.Ed."
        },
        {
            "catalogTitle": "ELP 6520",
            "section": "001",
            "courseTitle": "Ldrshp in Stdnt Affairs"
        },
        {
            "catalogTitle": "ELP 6520",
            "section": "002",
            "courseTitle": "Ldrshp in Stdnt Affairs"
        },
        {
            "catalogTitle": "ELP 6550",
            "section": "001",
            "courseTitle": "Student Affairs Admin"
        },
        {
            "catalogTitle": "ELP 6580",
            "section": "001",
            "courseTitle": "Multcltrlsm/Div High Ed"
        },
        {
            "catalogTitle": "ELP 6710",
            "section": "060",
            "courseTitle": "K-12 Internship"
        },
        {
            "catalogTitle": "ELP 6711",
            "section": "001",
            "courseTitle": "Internship (H.Ed.)"
        },
        {
            "catalogTitle": "ELP 7040",
            "section": "001",
            "courseTitle": "Quant Research Meth"
        },
        {
            "catalogTitle": "ELP 7220",
            "section": "001",
            "courseTitle": "Leadership Theory"
        },
        {
            "catalogTitle": "ELP 7460",
            "section": "001",
            "courseTitle": "Adv Ed Finance & Econ"
        },
        {
            "catalogTitle": "ELP 7480",
            "section": "001",
            "courseTitle": "Ldrshp Div & SJ in K-16"
        },
        {
            "catalogTitle": "ELP 7500",
            "section": "001",
            "courseTitle": "Foundations of H.Ed."
        },
        {
            "catalogTitle": "ELP 7520",
            "section": "001",
            "courseTitle": "Ldrshp in Stdnt Affairs"
        },
        {
            "catalogTitle": "ELP 7520",
            "section": "002",
            "courseTitle": "Ldrshp in Stdnt Affairs"
        },
        {
            "catalogTitle": "ELP 7550",
            "section": "001",
            "courseTitle": "Student Affairs Admin"
        },
        {
            "catalogTitle": "ELP 7580",
            "section": "001",
            "courseTitle": "Multcltrlsm/Div High Ed"
        },
        {
            "catalogTitle": "ELP 7600",
            "section": "001",
            "courseTitle": "Proposal Writing Semina"
        },
        {
            "catalogTitle": "ELP 7650",
            "section": "001",
            "courseTitle": "Ed Pol Cntr Practicum"
        },
        {
            "catalogTitle": "ELP 7960",
            "section": "002",
            "courseTitle": "Introduction to Inquiry"
        },
        {
            "catalogTitle": "ELP 7960",
            "section": "003",
            "courseTitle": "Appl Qualitat.  Rsrch. Methods"
        },
        {
            "catalogTitle": "ELP 7960",
            "section": "004",
            "courseTitle": "Latinos in Ed. Policy K-16"
        },
        {
            "catalogTitle": "ELP 7960",
            "section": "005",
            "courseTitle": "Professional Learning"
        },
        {
            "catalogTitle": "ELP 7960",
            "section": "006",
            "courseTitle": "Research Apprenticeship Course"
        },
        {
            "catalogTitle": "ELP 7960",
            "section": "007",
            "courseTitle": "Research Apprenticeship Course"
        },
        {
            "catalogTitle": "ELP 7960",
            "section": "008",
            "courseTitle": "Research Apprenticeship Course"
        },
        {
            "catalogTitle": "ELP 7960",
            "section": "009",
            "courseTitle": "Survey Design"
        },
        {
            "catalogTitle": "ELP 7990",
            "section": "001",
            "courseTitle": "Continuing Reg-Doc"
        }
    ]
}