{
    "courses": [
        {
            "catalogTitle": "LLFW 271",
            "section": "001",
            "courseTitle": "All About Coffee"
        },
        {
            "catalogTitle": "LLFW 299",
            "section": "001",
            "courseTitle": "Mastering Martinis"
        },
        {
            "catalogTitle": "LLFW 377",
            "section": "001",
            "courseTitle": "Value Wines of Spain"
        },
        {
            "catalogTitle": "LLFW 378",
            "section": "001",
            "courseTitle": "Value Wines of France"
        },
        {
            "catalogTitle": "LLFW 384",
            "section": "001",
            "courseTitle": "Scotch for the Sophisticate"
        },
        {
            "catalogTitle": "LLFW 386",
            "section": "001",
            "courseTitle": "Value Wines of Italy"
        },
        {
            "catalogTitle": "LLFW 438",
            "section": "002",
            "courseTitle": "A Walk Through the Wine Store"
        },
        {
            "catalogTitle": "LLFW 438",
            "section": "003",
            "courseTitle": "A Walk Through the Wine Store"
        },
        {
            "catalogTitle": "LLFW 447",
            "section": "001",
            "courseTitle": "Cheesemaking 101"
        },
        {
            "catalogTitle": "LLFW 466",
            "section": "001",
            "courseTitle": "Croissants"
        },
        {
            "catalogTitle": "LLFW 466",
            "section": "002",
            "courseTitle": "Croissants"
        },
        {
            "catalogTitle": "LLFW 482",
            "section": "001",
            "courseTitle": "Mixology"
        },
        {
            "catalogTitle": "LLFW 484",
            "section": "001",
            "courseTitle": "Fermenting Foods for Health"
        },
        {
            "catalogTitle": "LLFW 487",
            "section": "001",
            "courseTitle": "The Art of Ramen"
        },
        {
            "catalogTitle": "LLFW 488",
            "section": "001",
            "courseTitle": "Pizza from Scratch"
        },
        {
            "catalogTitle": "LLFW 489",
            "section": "001",
            "courseTitle": "Whiskeys of the World"
        },
        {
            "catalogTitle": "LLFW 490",
            "section": "001",
            "courseTitle": "Indian Market and Menu Tour"
        },
        {
            "catalogTitle": "LLFW 491",
            "section": "001",
            "courseTitle": "Taste of Utah - Wine and Choco"
        }
    ]
}