{
    "courses": [
        {
            "catalogTitle": "CVEEN 4910",
            "section": "001",
            "courseTitle": "Pro Pract. & Design"
        },
        {
            "catalogTitle": "CVEEN 5930",
            "section": "001",
            "courseTitle": "Independent Study"
        },
        {
            "catalogTitle": "CVEEN 6340",
            "section": "001",
            "courseTitle": "Adv Geotech Testing"
        },
        {
            "catalogTitle": "CVEEN 6920",
            "section": "002",
            "courseTitle": "Transport. Analysis Methods"
        },
        {
            "catalogTitle": "CVEEN 6930",
            "section": "001",
            "courseTitle": "Adv Indep Study"
        },
        {
            "catalogTitle": "CVEEN 6980",
            "section": "001",
            "courseTitle": "Faculty Consultation"
        },
        {
            "catalogTitle": "CVEEN 7430",
            "section": "001",
            "courseTitle": "Adv Subsurf Model"
        },
        {
            "catalogTitle": "CVEEN 7930",
            "section": "001",
            "courseTitle": "Adv Indep Study"
        },
        {
            "catalogTitle": "CVEEN 7970",
            "section": "001",
            "courseTitle": "Thesis Research - Ph D"
        },
        {
            "catalogTitle": "CVEEN 7970",
            "section": "014",
            "courseTitle": "Thesis Research - Ph D"
        },
        {
            "catalogTitle": "CVEEN 7980",
            "section": "001",
            "courseTitle": "Faculty Consultation"
        },
        {
            "catalogTitle": "CVEEN 7990",
            "section": "001",
            "courseTitle": "Cont Reg-Ph D"
        }
    ]
}