{
    "courses": [
        {
            "catalogTitle": "LLFW 236",
            "section": "001",
            "courseTitle": "How to Brew Beer"
        },
        {
            "catalogTitle": "LLFW 271",
            "section": "001",
            "courseTitle": "Coffee 101"
        },
        {
            "catalogTitle": "LLFW 295",
            "section": "001",
            "courseTitle": "World of Tea"
        },
        {
            "catalogTitle": "LLFW 305",
            "section": "001",
            "courseTitle": "Cocktails for Summer"
        },
        {
            "catalogTitle": "LLFW 317",
            "section": "001",
            "courseTitle": "Raw Foods"
        },
        {
            "catalogTitle": "LLFW 346",
            "section": "001",
            "courseTitle": "Eating Local Year-Round"
        },
        {
            "catalogTitle": "LLFW 371",
            "section": "001",
            "courseTitle": "Beer Tastings and Pairings"
        },
        {
            "catalogTitle": "LLFW 373",
            "section": "001",
            "courseTitle": "Summer Whites"
        },
        {
            "catalogTitle": "LLFW 403",
            "section": "001",
            "courseTitle": "Value Wines: Great Summer Sips"
        },
        {
            "catalogTitle": "LLFW 411",
            "section": "001",
            "courseTitle": "Roses of Provence"
        },
        {
            "catalogTitle": "LLFW 416",
            "section": "001",
            "courseTitle": "Gathering Wild Mushrooms"
        },
        {
            "catalogTitle": "LLFW 424",
            "section": "001",
            "courseTitle": "French Market Cooking"
        },
        {
            "catalogTitle": "LLFW 425",
            "section": "001",
            "courseTitle": "Spices"
        },
        {
            "catalogTitle": "LLFW 426",
            "section": "001",
            "courseTitle": "Market Tour"
        }
    ]
}